c108/__init__.py
c108/abc.py
c108/cli.py
c108/collections.py
c108/dataclasses.py
c108/dictify.py
c108/display.py
c108/formatters.py
c108/io.py
c108/json.py
c108/network.py
c108/numeric.py
c108/os.py
c108/scratch.py
c108/sentinels.py
c108/shutil.py
c108/tools.py
c108/unicode.py
c108/utils.py
c108/stubs/__init__.py
c108/stubs/__main__.py
c108/stubs/merge.py
c108/stubs/mergeable.py
c108/validators/__init__.py
c108/validators/constants.py
c108/validators/schemes.py
c108-0.2.0.dist-info/METADATA
c108-0.2.0.dist-info/WHEEL
c108-0.2.0.dist-info/licenses/LICENSE
c108-0.2.0.dist-info/RECORD
