Metadata-Version: 2.4
Name: c108
Version: 0.2.0
Summary: Curated core Python utilities with zero dependencies.
Project-URL: Docs, https://c108.readthedocs.io/
Project-URL: Source, https://github.com/C108-Lab/c108
Author: Carbon108
License: MIT
License-File: LICENSE
Keywords: c108,python
Requires-Python: >=3.10
Provides-Extra: dev
Requires-Dist: astropy<8.0,>=5.0; extra == 'dev'
Requires-Dist: jax<0.9,>=0.4; extra == 'dev'
Requires-Dist: numpy<3.0,>=1.24; extra == 'dev'
Requires-Dist: pandas<3.0,>=2.0; extra == 'dev'
Requires-Dist: pip>=24.0; extra == 'dev'
Requires-Dist: pygments>=2.17; extra == 'dev'
Requires-Dist: pytest-cov<8.0,>=5.0; extra == 'dev'
Requires-Dist: pytest-rerunfailures<17.0,>=12.0; extra == 'dev'
Requires-Dist: pytest<9.0,>=8.0; extra == 'dev'
Requires-Dist: ruff<1.0,>=0.1.0; extra == 'dev'
Requires-Dist: sympy<2.0,>=1.12; extra == 'dev'
Requires-Dist: tensorflow<3.0,>=2.13; extra == 'dev'
Requires-Dist: torch<3.0,>=2.0; extra == 'dev'
Requires-Dist: xdoctest<2.0,>=1.1.2; extra == 'dev'
Provides-Extra: ml
Requires-Dist: jax<0.9,>=0.4; extra == 'ml'
Requires-Dist: numpy<3.0,>=1.24; extra == 'ml'
Requires-Dist: pandas<3.0,>=2.0; extra == 'ml'
Requires-Dist: tensorflow<3.0,>=2.13; extra == 'ml'
Requires-Dist: torch<3.0,>=2.0; extra == 'ml'
Provides-Extra: sci
Requires-Dist: astropy<8.0,>=5.0; extra == 'sci'
Requires-Dist: numpy<3.0,>=1.24; extra == 'sci'
Requires-Dist: pandas<3.0,>=2.0; extra == 'sci'
Requires-Dist: sympy<2.0,>=1.12; extra == 'sci'
Provides-Extra: test
Requires-Dist: pytest-cov<8.0,>=5.0; extra == 'test'
Requires-Dist: pytest-rerunfailures<17.0,>=12.0; extra == 'test'
Requires-Dist: pytest<9.0,>=8.0; extra == 'test'
Requires-Dist: xdoctest<2.0,>=1.1.2; extra == 'test'
Provides-Extra: tools
Requires-Dist: pip>=24.0; extra == 'tools'
Requires-Dist: pygments>=2.17; extra == 'tools'
Requires-Dist: ruff<1.0,>=0.1.0; extra == 'tools'
